peachdb/__init__.py
peachdb/constants.py
peachdb/validators.py
peachdb/backends/__init__.py
peachdb/backends/backend_base.py
peachdb/backends/hnsw_backend.py
peachdb/backends/numpy_backend.py
peachdb/backends/torch_backend.py
peachdb/embedder/__init__.py
peachdb/embedder/utils.py
peachdb/embedder/containers/__init__.py
peachdb/embedder/containers/base.py
peachdb/embedder/containers/multimodal_imagebind.py
peachdb/embedder/containers/sentence_transformer.py
peachdb/embedder/models/__init__.py
peachdb/embedder/models/base.py
peachdb/embedder/models/multimodal_imagebind.py
peachdb/embedder/models/sentence_transformer.py
peachdb-0.1.0.dist-info/LICENSE
peachdb-0.1.0.dist-info/METADATA
peachdb-0.1.0.dist-info/WHEEL
peachdb-0.1.0.dist-info/dependency_links.txt
peachdb-0.1.0.dist-info/top_level.txt
peachdb-0.1.0.dist-info/RECORD
