Metadata-Version: 2.1
Name: peachdb
Version: 0.1.0
License: Apache License 2.0
Project-URL: Source on GitHub, https://github.com/peach-db/peachdb
Project-URL: Documentation, https://github.com/peach-db/peachdb/blob/master/README.md
Requires-Python: >=3.10
License-File: LICENSE
Requires-Dist: duckdb (==0.7.1)
Requires-Dist: fastapi[all]
Requires-Dist: torch
Requires-Dist: sentence-transformers
Requires-Dist: rich
Requires-Dist: black
Requires-Dist: isort
Requires-Dist: numpy
Requires-Dist: pandas
Requires-Dist: pyarrow
Requires-Dist: tqdm
Requires-Dist: fastapi
Requires-Dist: hnswlib
Requires-Dist: pyngrok (==6.0.0)
Requires-Dist: requests
Requires-Dist: modal-client
Requires-Dist: boto3
Requires-Dist: bumpversion
Requires-Dist: pre-commit
Requires-Dist: peachdb-imagebind
Requires-Dist: mypy
Requires-Dist: pandas-stubs
Requires-Dist: types-requests
